[
  {
    "commitId": "f9dee2998dcdcb89ff73e44c5f86ebcf9559dad1",
    "commitName": "iniciando",
    "commitTimestamp": 1772716655970,
    "testId": 0
  },
  {
    "numPassedTests": 1,
    "failedTests": 0,
    "numTotalTests": 1,
    "timestamp": 1772717049406,
    "success": true,
    "testId": 1
  },
  {
    "numPassedTests": 1,
    "failedTests": 0,
    "numTotalTests": 1,
    "timestamp": 1772717172078,
    "success": true,
    "testId": 1
  },
  {
    "commitId": "0be2bad81dbed5b3ddc6b6026ca8a26b5fd2d0fa",
    "commitName": "Feature: Totalizador agregado",
    "commitTimestamp": 1772717741234,
    "testId": 1
  },
  {
    "commitId": "e2c1558905c0c2137505070917636e2d4d72dff6",
    "commitName": "feat: mostrar la cantidad de items en pantalla",
    "commitTimestamp": 1772718360222,
    "testId": 2
  },
  {
    "commitId": "138dcb88e114e98d86af40e50a453223a5645ba4",
    "commitName": "Feature: Mostrar e ingresar el precio del item",
    "commitTimestamp": 1772718609523,
    "testId": 3
  },
  {
    "commitId": "e462d24842fc2bbc904b8874325ae30a30e6ee43",
    "commitName": "Feature:Multiplicacion del precio neto de cantidad de items y precio de items",
    "commitTimestamp": 1772718990622,
    "testId": 4
  },
  {
    "commitId": "1c856a5cab9ae824a3edea727e68980ac98911ac",
    "commitName": "Feature: Mostrar precio neto hecho en HTML, auno no implementa la lógica de multiplicacion, mas solo hay un lugar que reciba el dato",
    "commitTimestamp": 1772719289333,
    "testId": 5
  },
  {
    "commitId": "c5cd0ff14bc4067ed9b98580e1fa26b2fd2cb8ec",
    "commitName": "test: se añadio el file para poder hacer la modificacion",
    "commitTimestamp": 1772840554117,
    "testId": 6
  },
  {
    "numPassedTests": 0,
    "failedTests": 0,
    "numTotalTests": 0,
    "timestamp": 1772840623170,
    "success": false,
    "testId": 7
  },
  {
    "numPassedTests": 0,
    "failedTests": 0,
    "numTotalTests": 0,
    "timestamp": 1772840765155,
    "success": false,
    "testId": 7
  },
  {
    "numPassedTests": 1,
    "failedTests": 0,
    "numTotalTests": 1,
    "timestamp": 1772840862279,
    "success": true,
    "testId": 7
  },
  {
    "numPassedTests": 1,
    "failedTests": 0,
    "numTotalTests": 1,
    "timestamp": 1772840881464,
    "success": true,
    "testId": 7
  },
  {
    "commitId": "d56e41eac3183ae43931ef7872f633445f6e267f",
    "commitName": "docx: Funcionalidades añadidas en el README",
    "commitTimestamp": 1772841825786,
    "testId": 7
  },
  {
    "commitId": "bcf5ee31073473dbb510b6e9187dddd50792b3ea",
    "commitName": "test: Calcular precio neto implementado",
    "commitTimestamp": 1772841923219,
    "testId": 8
  },
  {
    "commitId": "38cb1cc5c3c750e8846f90f77c0c54b75c49f576",
    "commitName": "style: implementecion de html para taxes de CALIFORNIA implementado",
    "commitTimestamp": 1772842381311,
    "testId": 9
  },
  {
    "commitId": "b60e8205a0debf44af8b7c6c3b85710668df96c0",
    "commitName": "style: implementecion de html para taxes de CALIFORNIA implementado",
    "commitTimestamp": 1772842482746,
    "testId": 10
  },
  {
    "commitId": "4cb12c7ea9c27cc2aa970861b889f6dc7eef52e5",
    "commitName": "feature: calcular precio total + impuesto de california",
    "commitTimestamp": 1772843107362,
    "testId": 11
  },
  {
    "numPassedTests": 4,
    "failedTests": 0,
    "numTotalTests": 4,
    "timestamp": 1772843175068,
    "success": true,
    "testId": 12
  },
  {
    "commitId": "e8e8f6caa7c54bb5775d68caf1080e51a2862b45",
    "commitName": "docx: cambio pequeño realizado",
    "commitTimestamp": 1772843263183,
    "testId": 12
  },
  {
    "numPassedTests": 2,
    "failedTests": 0,
    "numTotalTests": 2,
    "timestamp": 1772843297979,
    "success": true,
    "testId": 13
  },
  {
    "commitId": "64e3e3fe824a7f0c81a2482c461d0731ab690a28",
    "commitName": "test: test de precio total de california añadido",
    "commitTimestamp": 1772843349127,
    "testId": 13
  },
  {
    "commitId": "2129eda74f1f868c7cff94e69f95a868a9e5c26a",
    "commitName": "refactor: para que el usuario pueda elegir el estado, implementado por ahora para california y alabama",
    "commitTimestamp": 1772844120709,
    "testId": 14
  },
  {
    "numPassedTests": 6,
    "failedTests": 0,
    "numTotalTests": 6,
    "timestamp": 1772844160157,
    "success": true,
    "testId": 15
  },
  {
    "commitId": "1c9d95b6e52b4f7fe53d4fd7ea835d1c556c09fc",
    "commitName": "feature: calcular precio total + impuesto de alabama",
    "commitTimestamp": 1772844445342,
    "testId": 15
  },
  {
    "numPassedTests": 6,
    "failedTests": 0,
    "numTotalTests": 6,
    "timestamp": 1772844888098,
    "success": true,
    "testId": 16
  },
  {
    "numPassedTests": 8,
    "failedTests": 0,
    "numTotalTests": 8,
    "timestamp": 1772844897506,
    "success": true,
    "testId": 16
  },
  {
    "commitId": "d26c4a82e50a376402828b8d44745205e1bc2899",
    "commitName": "feature: calcular precio total + impuesto de texas",
    "commitTimestamp": 1772845857970,
    "testId": 16
  },
  {
    "numPassedTests": 10,
    "failedTests": 0,
    "numTotalTests": 10,
    "timestamp": 1772845978173,
    "success": true,
    "testId": 17
  },
  {
    "commitId": "924dea09d7c9d18e07d22b2bec7f9e5d0e7cb429",
    "commitName": "feature: calcular precio total + impuesto de nevada",
    "commitTimestamp": 1772846654233,
    "testId": 17
  },
  {
    "numPassedTests": 12,
    "failedTests": 0,
    "numTotalTests": 12,
    "timestamp": 1772847060904,
    "success": true,
    "testId": 18
  },
  {
    "commitId": "ad2d4fcc0fe98986f411454d4f18d01bdbc495fb",
    "commitName": "feature: calcular precio total + impuesto de utah",
    "commitTimestamp": 1772847702998,
    "testId": 18
  },
  {
    "numPassedTests": 12,
    "failedTests": 0,
    "numTotalTests": 12,
    "timestamp": 1772847718053,
    "success": true,
    "testId": 19
  },
  {
    "commitId": "0dacca48a3ec07c91a10909555c9fc56b2d7d925",
    "commitName": "test:prueba hecha para todos los estados",
    "commitTimestamp": 1772847953506,
    "testId": 19
  },
  {
    "numPassedTests": 12,
    "failedTests": 1,
    "numTotalTests": 13,
    "timestamp": 1772923239763,
    "success": false,
    "testId": 20
  },
  {
    "numPassedTests": 12,
    "failedTests": 1,
    "numTotalTests": 13,
    "timestamp": 1772923598069,
    "success": false,
    "testId": 20
  },
  {
    "numPassedTests": 12,
    "failedTests": 1,
    "numTotalTests": 13,
    "timestamp": 1772923623861,
    "success": false,
    "testId": 20
  },
  {
    "numPassedTests": 13,
    "failedTests": 0,
    "numTotalTests": 13,
    "timestamp": 1772923658997,
    "success": true,
    "testId": 20
  },
  {
    "numPassedTests": 13,
    "failedTests": 0,
    "numTotalTests": 13,
    "timestamp": 1772923886971,
    "success": true,
    "testId": 20
  },
  {
    "numPassedTests": 13,
    "failedTests": 0,
    "numTotalTests": 13,
    "timestamp": 1772923963023,
    "success": true,
    "testId": 20
  },
  {
    "numPassedTests": 13,
    "failedTests": 0,
    "numTotalTests": 13,
    "timestamp": 1772923982058,
    "success": true,
    "testId": 20
  },
  {
    "numPassedTests": 12,
    "failedTests": 1,
    "numTotalTests": 13,
    "timestamp": 1772924411862,
    "success": false,
    "testId": 20
  },
  {
    "numPassedTests": 12,
    "failedTests": 1,
    "numTotalTests": 13,
    "timestamp": 1772924602087,
    "success": false,
    "testId": 20
  },
  {
    "numPassedTests": 13,
    "failedTests": 0,
    "numTotalTests": 13,
    "timestamp": 1772924699529,
    "success": true,
    "testId": 20
  },
  {
    "commitId": "3e04b3cbc7d165767827253b11b0c2f0c21e1401",
    "commitName": "feat: agregar el descuento por total de orden cuando es menor a 1000",
    "commitTimestamp": 1772924863536,
    "testId": 20
  },
  {
    "numPassedTests": 13,
    "failedTests": 1,
    "numTotalTests": 14,
    "timestamp": 1772925579046,
    "success": false,
    "testId": 21
  },
  {
    "numPassedTests": 14,
    "failedTests": 0,
    "numTotalTests": 14,
    "timestamp": 1772925671910,
    "success": true,
    "testId": 21
  },
  {
    "numPassedTests": 14,
    "failedTests": 0,
    "numTotalTests": 14,
    "timestamp": 1772925884237,
    "success": true,
    "testId": 21
  },
  {
    "numPassedTests": 13,
    "failedTests": 1,
    "numTotalTests": 14,
    "timestamp": 1772925894800,
    "success": false,
    "testId": 21
  },
  {
    "numPassedTests": 13,
    "failedTests": 1,
    "numTotalTests": 14,
    "timestamp": 1772926412003,
    "success": false,
    "testId": 21
  },
  {
    "numPassedTests": 14,
    "failedTests": 0,
    "numTotalTests": 14,
    "timestamp": 1772926427271,
    "success": true,
    "testId": 21
  },
  {
    "commitId": "36dec1bc32d834bee00a605b02329596b8eec5d6",
    "commitName": "feat: agregar el descuento por total de orden cuando es mayor o igual a 1000",
    "commitTimestamp": 1772926490010,
    "testId": 21
  },
  {
    "numPassedTests": 14,
    "failedTests": 1,
    "numTotalTests": 15,
    "timestamp": 1772926635039,
    "success": false,
    "testId": 22
  },
  {
    "numPassedTests": 14,
    "failedTests": 1,
    "numTotalTests": 15,
    "timestamp": 1772926690480,
    "success": false,
    "testId": 22
  },
  {
    "numPassedTests": 15,
    "failedTests": 0,
    "numTotalTests": 15,
    "timestamp": 1772926703152,
    "success": true,
    "testId": 22
  },
  {
    "numPassedTests": 15,
    "failedTests": 1,
    "numTotalTests": 16,
    "timestamp": 1772926939875,
    "success": false,
    "testId": 22
  },
  {
    "numPassedTests": 15,
    "failedTests": 1,
    "numTotalTests": 16,
    "timestamp": 1772926970272,
    "success": false,
    "testId": 22
  },
  {
    "numPassedTests": 16,
    "failedTests": 0,
    "numTotalTests": 16,
    "timestamp": 1772926985677,
    "success": true,
    "testId": 22
  },
  {
    "commitId": "6a3e531642761d05813e4e6f22b19df33e71c177",
    "commitName": "feat: se agrego el descuento por total de orden cuando es mayor o igual que 7000",
    "commitTimestamp": 1772927083540,
    "testId": 22
  },
  {
    "numPassedTests": 16,
    "failedTests": 1,
    "numTotalTests": 17,
    "timestamp": 1772927237807,
    "success": false,
    "testId": 23
  },
  {
    "numPassedTests": 16,
    "failedTests": 1,
    "numTotalTests": 17,
    "timestamp": 1772927259435,
    "success": false,
    "testId": 23
  },
  {
    "numPassedTests": 17,
    "failedTests": 0,
    "numTotalTests": 17,
    "timestamp": 1772927271878,
    "success": true,
    "testId": 23
  },
  {
    "commitId": "2a0d96a357e09a885839e4277ac45c7ab9ea774d",
    "commitName": "feat: se agrego el descuento por total de orden cuando es mayor o igual que 10000",
    "commitTimestamp": 1772927313937,
    "testId": 23
  },
  {
    "numPassedTests": 17,
    "failedTests": 1,
    "numTotalTests": 18,
    "timestamp": 1772927450159,
    "success": false,
    "testId": 24
  },
  {
    "numPassedTests": 16,
    "failedTests": 2,
    "numTotalTests": 18,
    "timestamp": 1772927468986,
    "success": false,
    "testId": 24
  },
  {
    "numPassedTests": 17,
    "failedTests": 1,
    "numTotalTests": 18,
    "timestamp": 1772927480569,
    "success": false,
    "testId": 24
  },
  {
    "numPassedTests": 18,
    "failedTests": 0,
    "numTotalTests": 18,
    "timestamp": 1772927572087,
    "success": true,
    "testId": 24
  },
  {
    "numPassedTests": 17,
    "failedTests": 1,
    "numTotalTests": 18,
    "timestamp": 1772927624804,
    "success": false,
    "testId": 24
  },
  {
    "numPassedTests": 18,
    "failedTests": 0,
    "numTotalTests": 18,
    "timestamp": 1772927638071,
    "success": true,
    "testId": 24
  },
  {
    "commitId": "ea5737d44dd02857ef230f7b5ac2d7176ff40510",
    "commitName": "feat: se agrego el descuento por total de orden cuando es mayor o igual que 30000",
    "commitTimestamp": 1772927662777,
    "testId": 24
  },
  {
    "numPassedTests": 18,
    "failedTests": 0,
    "numTotalTests": 18,
    "timestamp": 1772929261674,
    "success": true,
    "testId": 25
  },
  {
    "commitId": "7c65537013720682569d5cab67deba2f84deff79",
    "commitName": "feat: se agrego la estructura html y conexion con la logica del descuento",
    "commitTimestamp": 1772930277233,
    "testId": 25
  },
  {
    "numPassedTests": 18,
    "failedTests": 1,
    "numTotalTests": 19,
    "timestamp": 1772931152183,
    "success": false,
    "testId": 26
  },
  {
    "numPassedTests": 18,
    "failedTests": 1,
    "numTotalTests": 19,
    "timestamp": 1772931182458,
    "success": false,
    "testId": 26
  },
  {
    "numPassedTests": 19,
    "failedTests": 0,
    "numTotalTests": 19,
    "timestamp": 1772931471639,
    "success": true,
    "testId": 26
  },
  {
    "numPassedTests": 19,
    "failedTests": 0,
    "numTotalTests": 19,
    "timestamp": 1772931951026,
    "success": true,
    "testId": 26
  },
  {
    "commitId": "e929f0c92cbd27ffebc7a4bb141e6f928b92407b",
    "commitName": "feat: se muestra el precio con el descuento y impuesto de las categoria por defecto varios",
    "commitTimestamp": 1772932049439,
    "testId": 26
  },
  {
    "numPassedTests": 19,
    "failedTests": 0,
    "numTotalTests": 19,
    "timestamp": 1772932319125,
    "success": true,
    "testId": 27
  },
  {
    "numPassedTests": 19,
    "failedTests": 0,
    "numTotalTests": 19,
    "timestamp": 1772932686164,
    "success": true,
    "testId": 27
  },
  {
    "numPassedTests": 19,
    "failedTests": 1,
    "numTotalTests": 20,
    "timestamp": 1772932758309,
    "success": false,
    "testId": 27
  },
  {
    "numPassedTests": 20,
    "failedTests": 0,
    "numTotalTests": 20,
    "timestamp": 1772932778275,
    "success": true,
    "testId": 27
  },
  {
    "numPassedTests": 19,
    "failedTests": 1,
    "numTotalTests": 20,
    "timestamp": 1772932790905,
    "success": false,
    "testId": 27
  },
  {
    "numPassedTests": 20,
    "failedTests": 0,
    "numTotalTests": 20,
    "timestamp": 1772932803756,
    "success": true,
    "testId": 27
  },
  {
    "commitId": "c091fb25cb2621855a5aacf3ef41457bbb4f8550",
    "commitName": "feat: Se agrego el calculo para la categoria alimentos",
    "commitTimestamp": 1772932927829,
    "testId": 27
  },
  {
    "numPassedTests": 20,
    "failedTests": 1,
    "numTotalTests": 21,
    "timestamp": 1772933338483,
    "success": false,
    "testId": 28
  },
  {
    "numPassedTests": 21,
    "failedTests": 0,
    "numTotalTests": 21,
    "timestamp": 1772933458313,
    "success": true,
    "testId": 28
  },
  {
    "numPassedTests": 21,
    "failedTests": 0,
    "numTotalTests": 21,
    "timestamp": 1772933511859,
    "success": true,
    "testId": 28
  },
  {
    "numPassedTests": 20,
    "failedTests": 1,
    "numTotalTests": 21,
    "timestamp": 1772933563341,
    "success": false,
    "testId": 28
  },
  {
    "numPassedTests": 20,
    "failedTests": 1,
    "numTotalTests": 21,
    "timestamp": 1772933618967,
    "success": false,
    "testId": 28
  },
  {
    "numPassedTests": 20,
    "failedTests": 1,
    "numTotalTests": 21,
    "timestamp": 1772933639571,
    "success": false,
    "testId": 28
  },
  {
    "numPassedTests": 20,
    "failedTests": 1,
    "numTotalTests": 21,
    "timestamp": 1772933800070,
    "success": false,
    "testId": 28
  },
  {
    "numPassedTests": 21,
    "failedTests": 0,
    "numTotalTests": 21,
    "timestamp": 1772933870228,
    "success": true,
    "testId": 28
  },
  {
    "numPassedTests": 20,
    "failedTests": 1,
    "numTotalTests": 21,
    "timestamp": 1772933884211,
    "success": false,
    "testId": 28
  },
  {
    "numPassedTests": 20,
    "failedTests": 1,
    "numTotalTests": 21,
    "timestamp": 1772933896741,
    "success": false,
    "testId": 28
  },
  {
    "numPassedTests": 20,
    "failedTests": 1,
    "numTotalTests": 21,
    "timestamp": 1772933937796,
    "success": false,
    "testId": 28
  },
  {
    "numPassedTests": 21,
    "failedTests": 0,
    "numTotalTests": 21,
    "timestamp": 1772933947974,
    "success": true,
    "testId": 28
  },
  {
    "numPassedTests": 21,
    "failedTests": 0,
    "numTotalTests": 21,
    "timestamp": 1772933967220,
    "success": true,
    "testId": 28
  },
  {
    "commitId": "HEAD",
    "commitName": "feat: Se agrego el calculo para la categoria Bebidas",
    "commitTimestamp": 1772934018085,
    "testId": 28
  }
]